source_tiktok_marketing/__init__.py
source_tiktok_marketing/components/advertiser_ids_partition_router.py
source_tiktok_marketing/components/transformations.py
source_tiktok_marketing/manifest.yaml
source_tiktok_marketing/run.py
source_tiktok_marketing/source.py
airbyte_source_tiktok_marketing-4.7.0.dist-info/METADATA
airbyte_source_tiktok_marketing-4.7.0.dist-info/WHEEL
airbyte_source_tiktok_marketing-4.7.0.dist-info/entry_points.txt
airbyte_source_tiktok_marketing-4.7.0.dist-info/RECORD
