Metadata-Version: 2.3
Name: airbyte-source-tiktok-marketing
Version: 4.7.0
Summary: Source implementation for Tiktok Marketing.
License: MIT
Author: Airbyte
Author-email: contact@airbyte.io
Requires-Python: >=3.10,<3.12
Classifier: License :: OSI Approved :: MIT License
Classifier: Programming Language :: Python :: 3
Classifier: Programming Language :: Python :: 3.10
Classifier: Programming Language :: Python :: 3.11
Requires-Dist: airbyte-cdk (>=6,<7)
Requires-Dist: freezegun (>=1.1.0,<2.0.0)
Project-URL: Documentation, https://docs.airbyte.com/integrations/sources/tiktok-marketing
Project-URL: Homepage, https://airbyte.com
Project-URL: Repository, https://github.com/airbytehq/airbyte
